foliant/preprocessors/epsconvert.py
foliantcontrib.epsconvert-1.0.7.dist-info/LICENSE
foliantcontrib.epsconvert-1.0.7.dist-info/METADATA
foliantcontrib.epsconvert-1.0.7.dist-info/WHEEL
foliantcontrib.epsconvert-1.0.7.dist-info/top_level.txt
foliantcontrib.epsconvert-1.0.7.dist-info/RECORD
