Metadata-Version: 2.1
Name: foliantcontrib.epsconvert
Version: 1.0.7
Summary: EPS to PNG converter for Foliant.
Home-page: https://github.com/foliant-docs/foliantcontrib.epsconvert
Author: Artemy Lomov
Author-email: artemy@lomov.ru
License: MIT
Platform: any
Classifier: Development Status :: 5 - Production/Stable
Classifier: Environment :: Console
Classifier: Intended Audience :: Developers
Classifier: License :: OSI Approved :: MIT License
Classifier: Operating System :: OS Independent
Classifier: Programming Language :: Python
Classifier: Topic :: Documentation
Classifier: Topic :: Utilities
Requires-Dist: foliant (>=1.0.4)
